Metadata-Version: 2.4
Name: shandu
Version: 2.0.0
Summary: Deep research system with LangChain and LangGraph
Home-page: https://github.com/jolovicdev/shandu
Author: Dušan Jolović
Author-email: jolovic@pm.me
Project-URL: Source, https://github.com/jolovicdev/shandu
Keywords: research,ai,llm,langchain,langgraph,deepresearch,deepsearch,search
Classifier: Development Status :: 3 - Alpha
Classifier: Intended Audience :: Science/Research
Classifier: Intended Audience :: Developers
Classifier: License :: OSI Approved :: MIT License
Classifier: Programming Language :: Python :: 3
Classifier: Programming Language :: Python :: 3.9
Classifier: Programming Language :: Python :: 3.10
Classifier: Programming Language :: Python :: 3.11
Classifier: Topic :: Scientific/Engineering :: Artificial Intelligence
Classifier: Topic :: Software Development :: Libraries :: Python Modules
Requires-Python: >=3.9
License-File: LICENSE
Requires-Dist: langchain>=0.1.0
Requires-Dist: langchain-core>=0.1.0
Requires-Dist: langchain-openai>=0.0.5
Requires-Dist: langchain-community>=0.0.13
Requires-Dist: langgraph>=0.0.20
Requires-Dist: langchain-text-splitters>=0.0.1
Requires-Dist: pydantic>=2.0.0
Requires-Dist: click>=8.0.0
Requires-Dist: rich>=13.0.0
Requires-Dist: aiohttp>=3.8.0
Requires-Dist: asyncio>=3.4.3
Requires-Dist: beautifulsoup4>=4.12.0
Requires-Dist: trafilatura>=1.6.0
Requires-Dist: fake_useragent>=1.2.0
Requires-Dist: playwright>=1.40.0
Requires-Dist: tiktoken>=0.5.0
Requires-Dist: googlesearch-python>=1.2.3
Requires-Dist: wikipedia>=1.4.0
Requires-Dist: arxiv>=2.0.0
Requires-Dist: python-dotenv>=1.0.0
Dynamic: author
Dynamic: author-email
Dynamic: classifier
Dynamic: description
Dynamic: description-content-type
Dynamic: home-page
Dynamic: keywords
Dynamic: license-file
Dynamic: project-url
Dynamic: requires-dist
Dynamic: requires-python
Dynamic: summary
